src/__init__.py
waveform-0.0.1.dist-info/LICENSE
waveform-0.0.1.dist-info/METADATA
waveform-0.0.1.dist-info/WHEEL
waveform-0.0.1.dist-info/top_level.txt
waveform-0.0.1.dist-info/RECORD
