Metadata-Version: 2.1
Name: waveform
Version: 0.0.1
Summary: Waveform Container Class
Home-page: https://github.com/PhilippCo/waveform
Author: Philipp Cochems
Author-email: philipp.cochems@gmail.com
License: UNKNOWN
Platform: UNKNOWN
Classifier: Programming Language :: Python :: 3
Classifier: License :: OSI Approved :: MIT License
Classifier: Operating System :: OS Independent
Requires-Python: >=3.6
